MANIFEST.in
README.md
pyproject.toml
requirements-dev.txt
requirements-test.txt
requirements.txt
setup.cfg
setup.py
tox.ini
docs/standard.md
examples/__init__.py
examples/binary_adapter_example.py
examples/environment_example.py
examples/logger_test.py
examples/secret_example.py
locker/__about__.json
locker/__about__.py
locker/__init__.py
locker/binary_adapter.py
locker/client.py
locker/error.py
locker/logger.py
locker/ls_object.py
locker/ls_response.py
locker/object_classes.py
locker/util.py
locker/bin/locker_linux
locker/bin/locker_mac
locker/bin/locker_windows.exe
locker/data_mockup/environments.json
locker/data_mockup/secrets.json
locker/data_mockup/sync.json
locker/ls_resources/__init__.py
locker/ls_resources/environment.py
locker/ls_resources/error_object.py
locker/ls_resources/secret.py
locker/ls_resources/abstract/__init__.py
locker/ls_resources/abstract/api_resource.py
locker/ls_resources/abstract/createable_api_resource.py
locker/ls_resources/abstract/deletable_api_resource.py
locker/ls_resources/abstract/detailable_api_resource.py
locker/ls_resources/abstract/listable_api_resource.py
locker/ls_resources/abstract/singleton_api_resource.py
locker/ls_resources/abstract/updateable_api_resource.py
locker_secrets.egg-info/PKG-INFO
locker_secrets.egg-info/SOURCES.txt
locker_secrets.egg-info/dependency_links.txt
locker_secrets.egg-info/requires.txt
locker_secrets.egg-info/top_level.txt
tests/__init__.py
tests/test_binary_adapter.py
tests/test_client.py
tests/test_logger.py
tests/test_util.py